{
  "project_info": {
    "project_number": "853209566148",
    "project_id": "verification-62d71",
    "storage_bucket": "verification-62d71.appspot.com"
  },
  "client": [
    {
      "client_info": {
        "mobilesdk_app_id": "1:853209566148:android:9a56bdab88626474d5b291",
        "android_client_info": {
          "package_name": "app.my.otpverification"
        }
      },
      "oauth_client": [
        {
          "client_id": "853209566148-590t0h111h2n1gnv40kbbbjlk28jba5j.apps.googleusercontent.com",
          "client_type": 3
        }
      ],
      "api_key": [
        {
          "current_key": "AIzaSyAUZva94wdZr-rJkqe9WhI9ayf8QuPqQKQ"
        }
      ],
      "services": {
        "appinvite_service": {
          "other_platform_oauth_client": [
            {
              "client_id": "853209566148-590t0h111h2n1gnv40kbbbjlk28jba5j.apps.googleusercontent.com",
              "client_type": 3
            }
          ]
        }
      }
    }
  ],
  "configuration_version": "1"
}